dltoolset/__init__.py
dltoolset/gpu_tool.py
dltoolset-0.0.5.dist-info/LICENSE.txt
dltoolset-0.0.5.dist-info/METADATA
dltoolset-0.0.5.dist-info/WHEEL
dltoolset-0.0.5.dist-info/top_level.txt
dltoolset-0.0.5.dist-info/RECORD
